tests
indicstemmer
