Metadata-Version: 1.0
Name: indicstemmer
Version: 0.1
Summary: Malayalam word stemmer
Home-page: UNKNOWN
Author: Santhosh Thottingal
Author-email: santhosh.thottingal@gmail.com
License: LGPL-3.0
Platform: UNKNOWN
